csle_agents/__init__.py
csle_agents/__version__.py
csle_agents/agents/__init__.py
csle_agents/agents/base/__init__.py
csle_agents/agents/base/base_agent.py
csle_agents/agents/bayesian_optimization/__init__.py
csle_agents/agents/bayesian_optimization/bayes_opt_agent.py
csle_agents/agents/bayesian_optimization_emukit/__init__.py
csle_agents/agents/bayesian_optimization_emukit/bayes_opt_emukit_agent.py
csle_agents/agents/bayesian_optimization_emukit/bo/__init__.py
csle_agents/agents/bayesian_optimization_emukit/bo/bo_config.py
csle_agents/agents/bayesian_optimization_emukit/bo/bo_results.py
csle_agents/agents/bayesian_optimization_emukit/bo/acquisition/__init__.py
csle_agents/agents/bayesian_optimization_emukit/bo/acquisition/acquisition_function_type.py
csle_agents/agents/bayesian_optimization_emukit/bo/acquisition/acquisition_optimizer_type.py
csle_agents/agents/bayesian_optimization_emukit/bo/gp/__init__.py
csle_agents/agents/bayesian_optimization_emukit/bo/gp/gp_config.py
csle_agents/agents/bayesian_optimization_emukit/bo/kernel/__init__.py
csle_agents/agents/bayesian_optimization_emukit/bo/kernel/kernel_config.py
csle_agents/agents/bayesian_optimization_emukit/bo/kernel/kernel_type.py
csle_agents/agents/bayesian_optimization_emukit/bo/kernel/rbf_kernel_config.py
csle_agents/agents/c51_clean/__init__.py
csle_agents/agents/c51_clean/c51_clean_agent.py
csle_agents/agents/cma_es/__init__.py
csle_agents/agents/cma_es/cma_es_agent.py
csle_agents/agents/cross_entropy/__init__.py
csle_agents/agents/cross_entropy/cross_entropy_agent.py
csle_agents/agents/dfsp_local/__init__.py
csle_agents/agents/dfsp_local/dfsp_local_agent.py
csle_agents/agents/dfsp_local/dfsp_local_ppo_agent.py
csle_agents/agents/differential_evolution/__init__.py
csle_agents/agents/differential_evolution/differential_evolution_agent.py
csle_agents/agents/dqn/__init__.py
csle_agents/agents/dqn/dqn_agent.py
csle_agents/agents/dqn_clean/__init__.py
csle_agents/agents/dqn_clean/dqn_clean_agent.py
csle_agents-0.9.45.dist-info/METADATA
csle_agents-0.9.45.dist-info/WHEEL
csle_agents-0.9.45.dist-info/top_level.txt
csle_agents-0.9.45.dist-info/RECORD
