Metadata-Version: 2.1
Name: csle-agents
Version: 0.9.45
Summary: Reinforcement learning agents for CSLE
Author: Kim Hammar
Author-email: hammar.kim@gmail.com
Maintainer-email: Kim Hammar <kimham@kth.se>
License: ## creative commons
Project-URL: Homepage, https://kim-hammar.github.io/csle/
Project-URL: Source, https://github.com/Kim-Hammar/csle
Keywords: Reinforcement-Learning,Cyber-Security,Markov-Games,Markov-Decision-Processes
Platform: unix
Platform: linux
Classifier: Programming Language :: Python :: 3
Classifier: Programming Language :: Python :: 3 :: Only
Classifier: Programming Language :: Python :: 3.8
Classifier: Programming Language :: Python :: 3.9
Classifier: Programming Language :: Python :: 3.10
Classifier: Programming Language :: Python :: 3.11
Classifier: Intended Audience :: Science/Research
Requires-Python: >=3.8
Requires-Dist: csle-base>=0.9.45
Requires-Dist: csle-common>=0.9.45
Requires-Dist: csle-collector>=0.9.45
Requires-Dist: csle-cluster>=0.9.45
Requires-Dist: csle-attacker>=0.9.45
Requires-Dist: csle-defender>=0.9.45
Requires-Dist: csle-system-identification>=0.9.45
Requires-Dist: gym-csle-stopping-game>=0.9.45
Requires-Dist: gym-csle-apt-game>=0.9.45
Requires-Dist: gym-csle-cyborg>=0.9.45
Requires-Dist: gym-csle-intrusion-response-game>=0.9.45
Requires-Dist: csle-tolerance>=0.9.45
Requires-Dist: stable-baselines3>=2.0.0
Requires-Dist: pulp>=2.7.0
Requires-Dist: bayesian-optimization>=1.3.1
Requires-Dist: iteround>=1.0.4
Requires-Dist: emukit>=0.4.10
Requires-Dist: GPy>=1.10.0
Requires-Dist: numpy==1.23.5
Requires-Dist: cma==3.3.0
Provides-Extra: test
Requires-Dist: pytest>=6.0; extra == "test"
Requires-Dist: pytest-cov>=2.0; extra == "test"
Requires-Dist: pytest-mock>=3.6.0; extra == "test"
Requires-Dist: pytest-grpc>=0.8.0; extra == "test"
Requires-Dist: grpcio>=1.69.0; extra == "test"
Requires-Dist: grpcio-tools>=1.69.0; extra == "test"
Requires-Dist: mypy>=1.7.0; extra == "test"
Requires-Dist: mypy-extensions>=1.0.0; extra == "test"
Requires-Dist: mypy-protobuf>=3.5.0; extra == "test"
Requires-Dist: types-PyYAML>=6.0.12.11; extra == "test"
Requires-Dist: types-paramiko>=3.2.0.0; extra == "test"
Requires-Dist: types-protobuf>=5.29.1.20250208; extra == "test"
Requires-Dist: types-requests>=2.31.0.1; extra == "test"
Requires-Dist: types-urllib3>=1.26.25.13; extra == "test"
Requires-Dist: flake8>=6.1.0; extra == "test"
Requires-Dist: flake8-rst-docstrings>=0.3.0; extra == "test"
Requires-Dist: tox>=4.24.1; extra == "test"
Requires-Dist: sphinx>=5.3.0; extra == "test"
Requires-Dist: sphinxcontrib-napoleon>=0.7; extra == "test"
Requires-Dist: sphinx-rtd-theme>=1.1.1; extra == "test"
Requires-Dist: twine>=6.1.0; extra == "test"
Requires-Dist: build>=0.10.0; extra == "test"
